CHANGES.txt
ZPL.txt
bibliograph.core-configure.zcml
setup.py
bibliograph/__init__.py
bibliograph.core.egg-info/PKG-INFO
bibliograph.core.egg-info/SOURCES.txt
bibliograph.core.egg-info/dependency_links.txt
bibliograph.core.egg-info/entry_points.txt
bibliograph.core.egg-info/namespace_packages.txt
bibliograph.core.egg-info/not-zip-safe
bibliograph.core.egg-info/requires.txt
bibliograph.core.egg-info/top_level.txt
bibliograph/core/README.txt
bibliograph/core/__init__.py
bibliograph/core/bibutils.py
bibliograph/core/configure.zcml
bibliograph/core/encodings.py
bibliograph/core/interfaces.py
bibliograph/core/tests.py
bibliograph/core/utils.py
bibliograph/core/version_check.py
bibliograph/core/vocabulary.py