Metadata-Version: 1.0
Name: bibliograph.core
Version: 1.0.1
Summary: Core definitions of bibliograph packages
Home-page: http://pypi.python.org/pypi/bibliograph.core
Author: Tom Gross
Author-email: itconsense@gmail.com
License: ZPL 2.1
Keywords: bibtex bibliography xml endnote ris bibutils
Platform: UNKNOWN
Classifier: Framework :: Plone
Classifier: Framework :: Zope2
Classifier: Framework :: Zope3
Classifier: Programming Language :: Python
Classifier: Development Status :: 5 - Production/Stable
Classifier: Topic :: Software Development :: Libraries :: Python Modules
Classifier: License :: OSI Approved :: Zope Public License
